<?xml version="1.0" encoding="UTF-8"?>
<databaseChangeLog
        xmlns="http://www.liquibase.org/xml/ns/dbchangelog"
        xmlns:xsi="http://www.w3.org/2001/XMLSchema-instance"
        xmlns:pro="http://www.liquibase.org/xml/ns/pro"
        xsi:schemaLocation="http://www.liquibase.org/xml/ns/dbchangelog http://www.liquibase.org/xml/ns/dbchangelog/dbchangelog-4.4.xsd
      http://www.liquibase.org/xml/ns/pro http://www.liquibase.org/xml/ns/pro/liquibase-pro-4.5.xsd">
    <changeSet author="zsomborjoel" id="9adac4f4-b9d8-11ec-8422-0242ac120002">
        <createTable tableName="users">
            <column name="id" type="UUID">
                <constraints nullable="false" primaryKey="true" primaryKeyName="actor_pkey"/>
            </column>
            <column name="firstname" type="VARCHAR(255)"/>
            <column name="lastname" type="VARCHAR(255)"/>
            <column name="twitter" type="VARCHAR(15)"/>
        </createTable>
    </changeSet>
</databaseChangeLog>